ada_s3.py
ada_s3-0.0.0.dist-info/METADATA
ada_s3-0.0.0.dist-info/WHEEL
ada_s3-0.0.0.dist-info/top_level.txt
ada_s3-0.0.0.dist-info/RECORD
