Metadata-Version: 2.1
Name: ada-s3
Version: 0.0.0
Summary: pending
Author-email: michael <michael_chia7@msn.com>
